pytest_mini/__init__.py
pytest_mini/allureoperator.py
pytest_mini/constant.py
pytest_mini/fixture.py
pytest_mini/locator.py
pytest_mini/logoperator.py
pytest_mini/mini.py
pytest_mini/plugin.py
pytest_mini/timeoperator.py
pytest_mini/tools/allure-2.14.0/bin/allure
pytest_mini/tools/allure-2.14.0/bin/allure.bat
pytest_mini/tools/allure-2.14.0/config/allure-cucumber.yml
pytest_mini/tools/allure-2.14.0/config/allure-junit.yml
pytest_mini/tools/allure-2.14.0/config/allure.yml
pytest_mini/tools/allure-2.14.0/lib/allure-commandline-2.14.0.jar
pytest_mini/tools/allure-2.14.0/lib/allure-generator-2.14.0.jar
pytest_mini/tools/allure-2.14.0/lib/allure-model-2.13.0.jar
pytest_mini/tools/allure-2.14.0/lib/allure-plugin-api-2.14.0.jar
pytest_mini/tools/allure-2.14.0/lib/allure1-model-1.0.jar
pytest_mini/tools/allure-2.14.0/lib/annotations-15.0.jar
pytest_mini/tools/allure-2.14.0/lib/commons-beanutils-1.9.3.jar
pytest_mini/tools/allure-2.14.0/lib/commons-codec-1.11.jar
pytest_mini/tools/allure-2.14.0/lib/commons-collections-3.2.2.jar
pytest_mini/tools/allure-2.14.0/lib/commons-collections4-4.2.jar
pytest_mini/tools/allure-2.14.0/lib/commons-io-2.8.0.jar
pytest_mini/tools/allure-2.14.0/lib/commons-lang3-3.12.0.jar
pytest_mini/tools/allure-2.14.0/lib/commons-logging-1.2.jar
pytest_mini/tools/allure-2.14.0/lib/commons-text-1.3.jar
pytest_mini/tools/allure-2.14.0/lib/config/jetty-logging.properties
pytest_mini/tools/allure-2.14.0/lib/config/log4j.properties
pytest_mini/tools/allure-2.14.0/lib/flexmark-0.62.2.jar
pytest_mini/tools/allure-2.14.0/lib/flexmark-util-ast-0.62.2.jar
pytest_mini/tools/allure-2.14.0/lib/flexmark-util-builder-0.62.2.jar
pytest_mini/tools/allure-2.14.0/lib/flexmark-util-collection-0.62.2.jar
pytest_mini/tools/allure-2.14.0/lib/flexmark-util-data-0.62.2.jar
pytest_mini/tools/allure-2.14.0/lib/flexmark-util-dependency-0.62.2.jar
pytest_mini/tools/allure-2.14.0/lib/flexmark-util-format-0.62.2.jar
pytest_mini/tools/allure-2.14.0/lib/flexmark-util-html-0.62.2.jar
pytest_mini-0.1.19.dist-info/LICENSE
pytest_mini-0.1.19.dist-info/WHEEL
pytest_mini-0.1.19.dist-info/entry_points.txt
pytest_mini-0.1.19.dist-info/METADATA
pytest_mini-0.1.19.dist-info/RECORD
