Metadata-Version: 2.1
Name: pytest-mini
Version: 0.1.19
Summary: A plugin to test mp
Author: 听白
Author-email: 490336534@qq.com
Requires-Python: >=3.9,<4.0
Classifier: Programming Language :: Python :: 3
Classifier: Programming Language :: Python :: 3.9
Classifier: Programming Language :: Python :: 3.10
Classifier: Programming Language :: Python :: 3.11
Requires-Dist: Faker (>=15.3.3,<16.0.0)
Requires-Dist: PyYAML (>=6.0,<7.0)
Requires-Dist: allure-pytest (>=2.11.1,<3.0.0)
Requires-Dist: allure-python-commons (>=2.11.1,<3.0.0)
Requires-Dist: concurrent-log-handler (>=0.9.20,<0.10.0)
Requires-Dist: minium (>=1.3.1,<2.0.0)
Requires-Dist: pytest (>=7.2.0,<8.0.0)
Requires-Dist: pytest-assume (>=2.4.3,<3.0.0)
Requires-Dist: pytest-dependency (>=0.5.1,<0.6.0)
Requires-Dist: pytest-lazy-fixture (>=0.6.3,<0.7.0)
Requires-Dist: pytest-ordering (>=0.6,<0.7)
Requires-Dist: python-dateutil (>=2.8.2,<3.0.0)
Requires-Dist: requests (>=2.28.1,<3.0.0)
